<?xml version="1.0"?><analysis><industryName>BRITISH PETROLEUM</industryName><sampleNumber>1000</sampleNumber><laboratoryName>ABC LABORATORIES</laboratoryName><sampleDate>25022015</sampleDate><results><arsenic><arsenicResult>0.5128038370524042</arsenicResult><arsenicComplianceResult>exceeds</arsenicComplianceResult></arsenic><cadmium><cadmiumResult>0.3339266232233249</cadmiumResult><cadmiumComplianceResult>exceeds</cadmiumComplianceResult></cadmium><cyanides><cyanidesResult>1.7369439391560528</cyanidesResult><cyanidesComplianceResult>complies</cyanidesComplianceResult></cyanides><copper><copperResult>6.54368787221665</copperResult><copperComplianceResult>exceeds</copperComplianceResult></copper><chromium><chromiumResult>0.4966748153300291</chromiumResult><chromiumComplianceResult>complies</chromiumComplianceResult></chromium><mercury><mercuryResult>0.322777303888962</mercuryResult><mercuryComplianceResult>exceeds</mercuryComplianceResult></mercury><nickel><nickelResult>5.799345028588244</nickelResult><nickelComplianceResult>exceeds</nickelComplianceResult></nickel><lead><leadResult>5.041697153211365</leadResult><leadComplianceResult>exceeds</leadComplianceResult></lead><zinc><zincResult>21.979874699725634</zincResult><zincComplianceResult>exceeds</zincComplianceResult></zinc></results><compliance>Unsatisfactory</compliance></analysis>